{
  "usd": 179800,
  "eur": 210350,
  "gbp": 242900,
  "chf": 229750,
  "cad": 131200,
  "aud": 130150,
  "sek": 19250,
  "nok": 19550,
  "rub": 2455,
  "thb": 5555,
  "sgd": 141250,
  "hkd": 22950,
  "azn": 105900,
  "amd": 4885,
  "dkk": 28150,
  "aed": 48600,
  "jpy": 11400,
  "try": 3960,
  "cny": 26450,
  "sar": 47900,
  "inr": 1880,
  "myr": 45750,
  "afn": 2855,
  "kwd": 583100,
  "iqd": 13700,
  "bhd": 476350,
  "omr": 467600,
  "qar": 49300,
  "emami_coin": 195000000,
  "nim_coin": 100000000,
  "rob_coin": 54000000,
  "gold": 20467934,
  "last_update": "2026-05-13T11:45:20.246856"
}