{
  "usd": 159650,
  "eur": 182500,
  "gbp": 211450,
  "chf": 197550,
  "cad": 112600,
  "aud": 111100,
  "sek": 16550,
  "nok": 16400,
  "rub": 2150,
  "thb": 4815,
  "sgd": 123350,
  "hkd": 20350,
  "azn": 93800,
  "amd": 4335,
  "dkk": 24400,
  "aed": 43900,
  "jpy": 9885,
  "try": 3435,
  "cny": 23550,
  "sar": 42550,
  "inr": 1685,
  "myr": 38550,
  "afn": 2515,
  "kwd": 517150,
  "iqd": 12200,
  "bhd": 422300,
  "omr": 415200,
  "qar": 43800,
  "emami_coin": 163500000,
  "nim_coin": 85500000,
  "rob_coin": 48500000,
  "gold": 15844452,
  "last_update": "2026-06-23T08:30:46.027293"
}