{
  "usd": 188800,
  "eur": 215400,
  "gbp": 253350,
  "chf": 233000,
  "cad": 134300,
  "aud": 132200,
  "sek": 19500,
  "nok": 19500,
  "rub": 2400,
  "thb": 5610,
  "sgd": 146200,
  "hkd": 24100,
  "azn": 110850,
  "amd": 5160,
  "dkk": 28800,
  "aed": 51500,
  "jpy": 11600,
  "try": 4000,
  "cny": 27850,
  "sar": 50250,
  "inr": 1955,
  "myr": 46150,
  "afn": 2860,
  "kwd": 609500,
  "iqd": 14400,
  "bhd": 500600,
  "omr": 491050,
  "qar": 51800,
  "emami_coin": 183000000,
  "nim_coin": 94000000,
  "rob_coin": 52500000,
  "gold": 18167967,
  "last_update": "2026-07-20T17:30:30.335669"
}