{
  "usd": 177950,
  "eur": 203200,
  "gbp": 238500,
  "chf": 220150,
  "cad": 125550,
  "aud": 123800,
  "sek": 18300,
  "nok": 18200,
  "rub": 2310,
  "thb": 5345,
  "sgd": 137650,
  "hkd": 22700,
  "azn": 104450,
  "amd": 4845,
  "dkk": 27150,
  "aed": 49700,
  "jpy": 11000,
  "try": 3785,
  "cny": 26250,
  "sar": 47400,
  "inr": 1860,
  "myr": 43700,
  "afn": 2735,
  "kwd": 574850,
  "iqd": 13600,
  "bhd": 471950,
  "omr": 462400,
  "qar": 48850,
  "emami_coin": 181500000,
  "nim_coin": 95000000,
  "rob_coin": 54500000,
  "gold": 17590839,
  "last_update": "2026-07-11T04:45:28.320221"
}