{
  "usd": 176000,
  "eur": 204950,
  "gbp": 237100,
  "chf": 224200,
  "cad": 127200,
  "aud": 126400,
  "sek": 18950,
  "nok": 18950,
  "rub": 2435,
  "thb": 5410,
  "sgd": 137750,
  "hkd": 22450,
  "azn": 103500,
  "amd": 4775,
  "dkk": 27400,
  "aed": 47500,
  "jpy": 11000,
  "try": 3830,
  "cny": 26000,
  "sar": 46850,
  "inr": 1850,
  "myr": 44400,
  "afn": 2815,
  "kwd": 569400,
  "iqd": 13450,
  "bhd": 466000,
  "omr": 457750,
  "qar": 48300,
  "emami_coin": 185000000,
  "nim_coin": 95000000,
  "rob_coin": 54000000,
  "gold": 19323375,
  "last_update": "2026-06-02T08:00:34.231052"
}