{
  "usd": 179000,
  "eur": 204550,
  "gbp": 239250,
  "chf": 221900,
  "cad": 126350,
  "aud": 124200,
  "sek": 18500,
  "nok": 18300,
  "rub": 2335,
  "thb": 5365,
  "sgd": 138550,
  "hkd": 22850,
  "azn": 104800,
  "amd": 4875,
  "dkk": 27350,
  "aed": 49200,
  "jpy": 11050,
  "try": 3820,
  "cny": 26350,
  "sar": 48000,
  "inr": 1880,
  "myr": 43950,
  "afn": 2795,
  "kwd": 577500,
  "iqd": 13650,
  "bhd": 473700,
  "omr": 465500,
  "qar": 49000,
  "emami_coin": 181000000,
  "nim_coin": 94500000,
  "rob_coin": 54000000,
  "gold": 17867860,
  "last_update": "2026-07-08T09:15:30.042904"
}