{
  "usd": 183300,
  "eur": 209700,
  "gbp": 245500,
  "chf": 226850,
  "cad": 130400,
  "aud": 128000,
  "sek": 19000,
  "nok": 18950,
  "rub": 2365,
  "thb": 5485,
  "sgd": 142050,
  "hkd": 23400,
  "azn": 107500,
  "amd": 5000,
  "dkk": 28050,
  "aed": 50500,
  "jpy": 11300,
  "try": 3895,
  "cny": 27050,
  "sar": 48750,
  "inr": 1905,
  "myr": 44950,
  "afn": 2755,
  "kwd": 592150,
  "iqd": 14000,
  "bhd": 486150,
  "omr": 476750,
  "qar": 50150,
  "emami_coin": 181000000,
  "nim_coin": 94000000,
  "rob_coin": 54000000,
  "gold": 17867860,
  "last_update": "2026-07-14T16:45:31.947787"
}