{
  "usd": 193200,
  "eur": 219700,
  "gbp": 257200,
  "chf": 236100,
  "cad": 136950,
  "aud": 134800,
  "sek": 19850,
  "nok": 20150,
  "rub": 2480,
  "thb": 5730,
  "sgd": 149600,
  "hkd": 24650,
  "azn": 113650,
  "amd": 5280,
  "dkk": 29400,
  "aed": 52600,
  "jpy": 11800,
  "try": 4080,
  "cny": 28550,
  "sar": 51350,
  "inr": 2000,
  "myr": 47200,
  "afn": 2905,
  "kwd": 623250,
  "iqd": 14750,
  "bhd": 512450,
  "omr": 502500,
  "qar": 53150,
  "emami_coin": 188500000,
  "nim_coin": 96000000,
  "rob_coin": 54000000,
  "gold": 18807424,
  "last_update": "2026-07-24T14:45:22.631519"
}