{
  "usd": 173500,
  "eur": 201400,
  "gbp": 232500,
  "chf": 219800,
  "cad": 125200,
  "aud": 123500,
  "sek": 18600,
  "nok": 18650,
  "rub": 2445,
  "thb": 5305,
  "sgd": 135600,
  "hkd": 22150,
  "azn": 102250,
  "amd": 4715,
  "dkk": 26950,
  "aed": 47600,
  "jpy": 10900,
  "try": 3780,
  "cny": 25600,
  "sar": 46250,
  "inr": 1805,
  "myr": 43600,
  "afn": 2775,
  "kwd": 560500,
  "iqd": 13250,
  "bhd": 460150,
  "omr": 451250,
  "qar": 47600,
  "emami_coin": 182000000,
  "nim_coin": 94000000,
  "rob_coin": 52500000,
  "gold": 18585807,
  "last_update": "2026-05-28T13:45:30.827632"
}