{
  "usd": 192900,
  "eur": 220700,
  "gbp": 259300,
  "chf": 238750,
  "cad": 137550,
  "aud": 134550,
  "sek": 20000,
  "nok": 20000,
  "rub": 2465,
  "thb": 5735,
  "sgd": 149350,
  "hkd": 24600,
  "azn": 113200,
  "amd": 5285,
  "dkk": 29500,
  "aed": 52900,
  "jpy": 11850,
  "try": 4090,
  "cny": 28500,
  "sar": 51350,
  "inr": 2005,
  "myr": 47100,
  "afn": 2920,
  "kwd": 624150,
  "iqd": 14750,
  "bhd": 512150,
  "omr": 502200,
  "qar": 52850,
  "emami_coin": 189000000,
  "nim_coin": 96500000,
  "rob_coin": 53500000,
  "gold": 18698924,
  "last_update": "2026-07-19T11:45:27.431372"
}