{
  "usd": 161850,
  "eur": 184450,
  "gbp": 213900,
  "chf": 200200,
  "cad": 114100,
  "aud": 112300,
  "sek": 16700,
  "nok": 16550,
  "rub": 2170,
  "thb": 4875,
  "sgd": 124900,
  "hkd": 20650,
  "azn": 95400,
  "amd": 4395,
  "dkk": 24650,
  "aed": 44500,
  "jpy": 10000,
  "try": 3480,
  "cny": 23900,
  "sar": 43100,
  "inr": 1710,
  "myr": 39100,
  "afn": 2550,
  "kwd": 523750,
  "iqd": 12350,
  "bhd": 429100,
  "omr": 420950,
  "qar": 44400,
  "emami_coin": 163000000,
  "nim_coin": 85500000,
  "rob_coin": 49000000,
  "gold": 15965880,
  "last_update": "2026-06-24T01:45:32.027916"
}