{
  "usd": 193500,
  "eur": 221350,
  "gbp": 260150,
  "chf": 239500,
  "cad": 137950,
  "aud": 134950,
  "sek": 20050,
  "nok": 20050,
  "rub": 2470,
  "thb": 5755,
  "sgd": 149800,
  "hkd": 24700,
  "azn": 113550,
  "amd": 5300,
  "dkk": 29600,
  "aed": 52700,
  "jpy": 11900,
  "try": 4105,
  "cny": 28550,
  "sar": 51500,
  "inr": 2010,
  "myr": 47250,
  "afn": 2930,
  "kwd": 626100,
  "iqd": 14800,
  "bhd": 513750,
  "omr": 503750,
  "qar": 53000,
  "emami_coin": 189000000,
  "nim_coin": 96500000,
  "rob_coin": 53500000,
  "gold": 18802807,
  "last_update": "2026-07-19T13:45:26.653422"
}