{
  "usd": 195400,
  "eur": 223550,
  "gbp": 262700,
  "chf": 241850,
  "cad": 139300,
  "aud": 136300,
  "sek": 20250,
  "nok": 20250,
  "rub": 2495,
  "thb": 5810,
  "sgd": 151300,
  "hkd": 24900,
  "azn": 114650,
  "amd": 5355,
  "dkk": 29900,
  "aed": 52700,
  "jpy": 12050,
  "try": 4145,
  "cny": 28850,
  "sar": 52000,
  "inr": 2030,
  "myr": 47700,
  "afn": 2960,
  "kwd": 632250,
  "iqd": 14950,
  "bhd": 518800,
  "omr": 508700,
  "qar": 53500,
  "emami_coin": 190000000,
  "nim_coin": 97000000,
  "rob_coin": 54500000,
  "gold": 19114455,
  "last_update": "2026-07-18T16:30:38.388720"
}