{
  "usd": 175600,
  "eur": 204450,
  "gbp": 236950,
  "chf": 224700,
  "cad": 127100,
  "aud": 125850,
  "sek": 18950,
  "nok": 19000,
  "rub": 2460,
  "thb": 5410,
  "sgd": 137500,
  "hkd": 22400,
  "azn": 103200,
  "amd": 4790,
  "dkk": 27350,
  "aed": 48000,
  "jpy": 11050,
  "try": 3840,
  "cny": 25850,
  "sar": 46950,
  "inr": 1845,
  "myr": 44400,
  "afn": 2810,
  "kwd": 567600,
  "iqd": 13450,
  "bhd": 467300,
  "omr": 456700,
  "qar": 48200,
  "emami_coin": 185000000,
  "nim_coin": 95000000,
  "rob_coin": 53000000,
  "gold": 19417793,
  "last_update": "2026-05-25T12:00:31.487679"
}